prdc/__init__.py
prdc/prdc.py
prdc-0.2.dist-info/LICENSE.md
prdc-0.2.dist-info/METADATA
prdc-0.2.dist-info/WHEEL
prdc-0.2.dist-info/top_level.txt
prdc-0.2.dist-info/RECORD
