Metadata-Version: 2.1
Name: prdc
Version: 0.2
Summary: Compute precision, recall, density, and coverage metrics for two sets of vectors.
Home-page: https://github.com/clovaai/prdc
Author: NAVER Corp.
License: UNKNOWN
Platform: UNKNOWN
Classifier: Programming Language :: Python :: 3
Classifier: License :: OSI Approved :: MIT License
Classifier: Operating System :: OS Independent
Requires-Dist: numpy
Requires-Dist: scikit-learn
Requires-Dist: scipy
Requires-Dist: joblib
